{"华为": 9, "拟": 1, "制定": 2, "连接器": 6, "标准": 3, "全力": 1, "推进": 1, "自主": 3, "可控": 3, "----------------": 1, "美国": 2, "政府": 1, "列入": 1, "实体": 2, "清单": 4, "高度": 1, "重视": 1, "核心": 2, "技术": 3, "基础": 1, "器件": 1, "可控性": 1, "安全性": 1, "加快": 1, "产品": 1, "软硬件": 1, "国产": 2, "替代": 1, "速度": 1, "业内": 2, "人士": 2, "透露": 1, "计划": 1, "点评": 1, "形象": 1, "理解": 1, "座": 1, "传输": 1, "信号": 1, "能量": 1, "桥梁": 1, "通讯": 1, "军工": 1, "汽车": 1, "行业": 1, "海思": 1, "芯片": 1, "转正": 1, "鸿蒙": 1, "系统": 1, "即将": 2, "面世": 1, "推出": 1, "路上": 1, "追求": 1, "元件": 1, "国产化": 1, "步伐": 1, "从未": 1, "停止": 4, "预计": 1, "减弱": 1, "外国": 1, "供应商": 1, "依赖": 1, "程度": 1, "选择": 1, "拥抱": 1, "拥有": 1, "优势": 1, "龙头": 1, "企业": 4, "立讯": 1, "精密": 1, "002475": 1, "润": 1, "电子": 1, "002055": 1, "太": 1, "辰光": 1, "300570": 1, "商务部": 3, "回应": 2, "美": 2, "管制": 3, "打压": 3, "中国": 4, "今日": 1, "例行": 1, "发布会": 1, "新闻": 1, "发言人": 1, "高峰": 1, "公司": 1, "市场": 1, "出口": 1, "敦促": 1, "美方": 1, "落实": 1, "承诺": 1, "尽快": 1, "动用": 1, "国家": 1, "力量": 1, "错误": 1, "做法": 1, "……": 1, "详情": 1, "点击": 1, "O": 1, "​": 1}